<?xml version="1.0" encoding="utf-8"?><Defs>

  <SoundDef>
    <defName>RT_T72VehicleEngine</defName>
    <sustain>true</sustain>
    <context>MapOnly</context>
    <maxSimultaneous>1</maxSimultaneous>  
    <priorityMode>PrioritizeNearest</priorityMode>  
    
	  <subSounds>
      <li>
        <muteWhenPaused>True</muteWhenPaused>      
        <grains>
          <li Class="AudioGrain_Clip">
            <clipPath>T72EngineWorking_Sustainer</clipPath>
          </li>
        </grains>      
        <pitchRange>0.99~1.01</pitchRange>
        <volumeRange>30~30</volumeRange>
        <sustainAttack>2.5</sustainAttack>      
        <sustainRelease>2.5</sustainRelease>
      </li>
    </subSounds>
  </SoundDef>

  <SoundDef>
    <defName>RT_BMPVehicleEngine</defName>
    <sustain>true</sustain>
    <context>MapOnly</context>
    <maxSimultaneous>1</maxSimultaneous>  
    <priorityMode>PrioritizeNearest</priorityMode>  
    
	  <subSounds>
      <li>
        <muteWhenPaused>True</muteWhenPaused>      
        <grains>
          <li Class="AudioGrain_Clip">
            <clipPath>BMPEngineWorking_Sustainer</clipPath>
          </li>
        </grains>      
        <pitchRange>0.99~1.01</pitchRange>
        <volumeRange>30~30</volumeRange>
        <sustainAttack>2.5</sustainAttack>      
        <sustainRelease>2.5</sustainRelease>
      </li>
    </subSounds>
  </SoundDef>

  <SoundDef>
    <defName>RT_WheeledVehicleEngine</defName>
    <sustain>true</sustain>
    <context>MapOnly</context>
    <maxSimultaneous>1</maxSimultaneous>  
    <priorityMode>PrioritizeNearest</priorityMode>  
    
	  <subSounds>
      <li>
        <muteWhenPaused>True</muteWhenPaused>      
        <grains>
          <li Class="AudioGrain_Clip">
            <clipPath>WheeledEngineWorking_Sustainer</clipPath>
          </li>
        </grains>      
        <pitchRange>0.99~1.01</pitchRange>
        <volumeRange>30~30</volumeRange>
        <sustainAttack>2.5</sustainAttack>      
        <sustainRelease>2.5</sustainRelease>
      </li>
    </subSounds>
  </SoundDef>

  <SoundDef>
    <defName>VVE_VehicleDeploying</defName>
    <sustain>true</sustain>
    <context>MapOnly</context>
    <maxSimultaneous>1</maxSimultaneous>  
    <priorityMode>PrioritizeNearest</priorityMode>  
    
	<subSounds>
      <li>
        <muteWhenPaused>True</muteWhenPaused>      
        <grains>
          <li Class="AudioGrain_Clip">
            <clipPath>VehicleDeploying_Sustainer</clipPath>
          </li>
        </grains>      
        <pitchRange>0.99~1.01</pitchRange>
        <volumeRange>45~45</volumeRange>
        <sustainAttack>2.5</sustainAttack>      
        <sustainRelease>2.5</sustainRelease>
      </li>
    </subSounds>
  </SoundDef>
  
  <SoundDef>
    <defName>RT_TigerVehicleEngine</defName>
    <sustain>true</sustain>
    <context>MapOnly</context>
    <maxSimultaneous>1</maxSimultaneous>  
    <priorityMode>PrioritizeNearest</priorityMode>  
    
	  <subSounds>
      <li>
        <muteWhenPaused>True</muteWhenPaused>      
        <grains>
          <li Class="AudioGrain_Clip">
            <clipPath>TigerEngineWorking_Sustainer</clipPath>
          </li>
        </grains>      
        <pitchRange>0.99~1.01</pitchRange>
        <volumeRange>20~20</volumeRange>
        <sustainAttack>2.5</sustainAttack>      
        <sustainRelease>2.5</sustainRelease>
      </li>
    </subSounds>
  </SoundDef>

  <SoundDef>
    <defName>RT_PantherVehicleEngine</defName>
    <sustain>true</sustain>
    <context>MapOnly</context>
    <maxSimultaneous>1</maxSimultaneous>  
    <priorityMode>PrioritizeNearest</priorityMode>  
    
	  <subSounds>
      <li>
        <muteWhenPaused>True</muteWhenPaused>      
        <grains>
          <li Class="AudioGrain_Clip">
            <clipPath>PantherEngineWorking_Sustainer</clipPath>
          </li>
        </grains>      
        <pitchRange>0.99~1.01</pitchRange>
        <volumeRange>30~30</volumeRange>
        <sustainAttack>2.5</sustainAttack>      
        <sustainRelease>2.5</sustainRelease>
      </li>
    </subSounds>
  </SoundDef>

  <SoundDef>
    <defName>RT_PzIVVehicleEngine</defName>
    <sustain>true</sustain>
    <context>MapOnly</context>
    <maxSimultaneous>1</maxSimultaneous>  
    <priorityMode>PrioritizeNearest</priorityMode>  
    
	  <subSounds>
      <li>
        <muteWhenPaused>True</muteWhenPaused>      
        <grains>
          <li Class="AudioGrain_Clip">
            <clipPath>PzIVEngineWorking_Sustainer</clipPath>
          </li>
        </grains>      
        <pitchRange>0.99~1.01</pitchRange>
        <volumeRange>30~30</volumeRange>
        <sustainAttack>2.5</sustainAttack>      
        <sustainRelease>2.5</sustainRelease>
      </li>
    </subSounds>
  </SoundDef>

  <SoundDef>
    <defName>RT_38tVehicleEngine</defName>
    <sustain>true</sustain>
    <context>MapOnly</context>
    <maxSimultaneous>1</maxSimultaneous>  
    <priorityMode>PrioritizeNearest</priorityMode>  
    
	  <subSounds>
      <li>
        <muteWhenPaused>True</muteWhenPaused>      
        <grains>
          <li Class="AudioGrain_Clip">
            <clipPath>38tEngineWorking_Sustainer</clipPath>
          </li>
        </grains>      
        <pitchRange>0.99~1.01</pitchRange>
        <volumeRange>20~20</volumeRange>
        <sustainAttack>2.5</sustainAttack>      
        <sustainRelease>2.5</sustainRelease>
      </li>
    </subSounds>
  </SoundDef>

  <SoundDef>
    <defName>VVE_VehicleEngineHeavy</defName>
    <sustain>true</sustain>
    <context>MapOnly</context>
    <maxSimultaneous>1</maxSimultaneous>  
    <priorityMode>PrioritizeNearest</priorityMode>  
    <subSounds>
      <li>
        <muteWhenPaused>True</muteWhenPaused>      
        <grains>
          <li Class="AudioGrain_Clip">
            <clipPath>VehicleEngineHeavy_Sustainer</clipPath>
          </li>
        </grains>      
        <pitchRange>0.99~1.01</pitchRange>
        <volumeRange>25~25</volumeRange>
        <sustainAttack>2.5</sustainAttack>      
        <sustainRelease>2.5</sustainRelease>
      </li>
    </subSounds>
  </SoundDef>
  
  <SoundDef>
    <defName>VVE_VehicleRotorAirplane</defName>
    <sustain>true</sustain>
    <context>MapOnly</context>
    <maxSimultaneous>1</maxSimultaneous>  
    <priorityMode>PrioritizeNearest</priorityMode>  
    <subSounds>
      <li>
        <muteWhenPaused>True</muteWhenPaused>      
        <grains>
          <li Class="AudioGrain_Clip">
            <clipPath>VehicleRotorAirplane_Sustainer</clipPath>
          </li>
        </grains>      
        <pitchRange>0.99~1.01</pitchRange>
        <volumeRange>35~35</volumeRange>
        <sustainAttack>2.5</sustainAttack>      
        <sustainRelease>2.5</sustainRelease>
      </li>
    </subSounds>
  </SoundDef>
  
  <SoundDef>
    <defName>VVE_VehicleRotorHeavyHelicopter</defName>
    <sustain>true</sustain>
    <context>MapOnly</context>
    <maxSimultaneous>1</maxSimultaneous>  
    <priorityMode>PrioritizeNearest</priorityMode>  
    <subSounds>
      <li>
        <muteWhenPaused>True</muteWhenPaused>      
        <grains>
          <li Class="AudioGrain_Clip">
            <clipPath>VehicleRotorHeavyHelicopter_Sustainer</clipPath>
          </li>
        </grains>      
        <pitchRange>0.99~1.01</pitchRange>
        <volumeRange>35~35</volumeRange>
        <sustainAttack>2.5</sustainAttack>      
        <sustainRelease>2.5</sustainRelease>
      </li>
    </subSounds>
  </SoundDef>
</Defs>
